{"Header":{"Name":"Trial 1.3","ViewUrl":"https://pmnplayground-2.popmednet.org/querycomposer/summaryview?ID=e4176a8e-3d02-409c-84b8-aa7000c43925","SubmittedOn":"2019-06-18T15:55:34.603Z"},"Where":{"Criteria":[{"ID":"195ad343-d6b5-449d-bed6-dedeac8e6d49","Name":"Group 1","Criteria":[{"ID":"e63257b8-4356-44f2-bc9f-15cb87816f16","Name":"i_Trial","Operator":0,"Criteria":[],"Terms":[{"Operator":1,"Type":"56a38f6d-993a-4953-bcb9-11bdd809c0b4","Values":{"Trial":"ADAPTABLE_2"},"Criteria":[],"Design":{}}],"Type":0},{"ID":"ab4887a7-73eb-4c11-9288-bc349b68c263","Name":"i_Sex","Operator":0,"Criteria":[],"Terms":[{"Operator":1,"Type":"71b4545c-345b-48b2-af5e-f84dc18e4e1a","Values":{"Sex":"3"},"Criteria":[],"Design":{}}],"Type":0}],"Terms":[]}]},"Select":{"Fields":[{"FieldName":"Trial","Type":"56a38f6d-993a-4953-bcb9-11bdd809c0b4","GroupBy":null,"StratifyBy":null,"Aggregate":null,"Select":[],"OrderBy":0},{"FieldName":"Trial_Count","Type":"56a38f6d-993a-4953-bcb9-11bdd809c0b4","GroupBy":null,"StratifyBy":null,"Aggregate":1,"Select":[],"OrderBy":0}]},"TemporalEvents":[]}