{"ID":null,"ResponseDateTime":"2017-11-27T20:25:37.8634832+00:00","RequestID":"c4a1b31b-e382-45fd-9172-a83800fc929f","Errors":null,"Results":[[{"Hispanic":"Pablo","Race":"04","Patients":1,"LowThreshold":false},{"Hispanic":"Sebastian","Race":"06","Patients":1,"LowThreshold":false},{"Hispanic":"Tanya","Race":"07","Patients":1,"LowThreshold":false}]],"LowCellThrehold":null,"Properties":[{"Name":"Hispanic","Type":"System.String","As":"Hispanic","Aggregate":null},{"Name":"Race","Type":"System.String","As":"Race","Aggregate":null},{"Name":"PatientID","Type":"System.Int32","As":"Patients","Aggregate":"Sum"},{"Name":"LowThreshold","Type":"System.Boolean","As":"LowThreshold","Aggregate":null}],"Aggregation":{"GroupBy":["Hispanic","Race"],"Select":[{"Name":"Hispanic","Type":"System.String","As":"Hispanic","Aggregate":null},{"Name":"Race","Type":"System.String","As":"Race","Aggregate":null},{"Name":"PatientID","Type":"System.Int32","As":"Patients","Aggregate":"Sum"}],"Name":null}}